mathy_alpha_sm/__init__.py
mathy_alpha_sm/model.config.json
mathy_alpha_sm/model/saved_model.pb
mathy_alpha_sm/model/variables/variables.data-00000-of-00001
mathy_alpha_sm/model/variables/variables.index
mathy_alpha_sm-0.8.1.dist-info/METADATA
mathy_alpha_sm-0.8.1.dist-info/WHEEL
mathy_alpha_sm-0.8.1.dist-info/top_level.txt
mathy_alpha_sm-0.8.1.dist-info/RECORD
